{
  "guideline": "paediatric-urology",
  "chapter": "rare-conditions-in-childhood",
  "url": "https://uroweb.org/guidelines/paediatric-urology/chapter/rare-conditions-in-childhood",
  "headings": [
    {
      "level": 2,
      "text": "1. INTRODUCTION",
      "anchor": "#1-introduction"
    },
    {
      "level": 3,
      "text": "1.1. Aim",
      "anchor": "#1-1-aim"
    },
    {
      "level": 3,
      "text": "1.2. Panel composition",
      "anchor": "#1-2-panel-composition"
    },
    {
      "level": 3,
      "text": "1.3. Available publications",
      "anchor": "#1-3-available-publications"
    },
    {
      "level": 3,
      "text": "1.4. Publication history",
      "anchor": "#1-4-publication-history"
    },
    {
      "level": 3,
      "text": "1.5. Summary of changes",
      "anchor": "#1-5-summary-of-changes"
    },
    {
      "level": 2,
      "text": "2. METHODS",
      "anchor": "#2-methods"
    },
    {
      "level": 3,
      "text": "2.1. Introduction",
      "anchor": "#2-1-introduction"
    },
    {
      "level": 3,
      "text": "2.2. Peer review",
      "anchor": "#2-2-peer-review"
    },
    {
      "level": 2,
      "text": "3. PHIMOSIS AND OTHER ABNORMALITIES OF THE PENILE SKIN",
      "anchor": "#3-phimosis-and-other-abnormalities-of-the-penile-skin"
    },
    {
      "level": 3,
      "text": "3.1. Terminology, epidemiology and pathophysiology",
      "anchor": "#3-1-terminology-epidemiology-and-pathophysiology"
    },
    {
      "level": 3,
      "text": "3.2. Classification and diagnostic evaluation",
      "anchor": "#3-2-classification-and-diagnostic-evaluation"
    },
    {
      "level": 3,
      "text": "3.3. Management",
      "anchor": "#3-3-management"
    },
    {
      "level": 3,
      "text": "3.4. Complications",
      "anchor": "#3-4-complications"
    },
    {
      "level": 3,
      "text": "3.5. Follow-up",
      "anchor": "#3-5-follow-up"
    },
    {
      "level": 3,
      "text": "3.6. Summary of evidence and recommendations for the management of phimosis",
      "anchor": "#3-6-summary-of-evidence-and-recommendations-for-the-management-of-phimosis"
    },
    {
      "level": 2,
      "text": "4. MANAGEMENT OF UNDESCENDED TESTES",
      "anchor": "#4-management-of-undescended-testes"
    },
    {
      "level": 3,
      "text": "4.1. Background",
      "anchor": "#4-1-background"
    },
    {
      "level": 3,
      "text": "4.2. Classification",
      "anchor": "#4-2-classification"
    },
    {
      "level": 4,
      "text": "4.2.1. Palpable testes",
      "anchor": "#4-2-1-palpable-testes"
    },
    {
      "level": 4,
      "text": "4.2.2. Nonpalpable testes",
      "anchor": "#4-2-2-nonpalpable-testes"
    },
    {
      "level": 3,
      "text": "4.3. Diagnostic evaluation",
      "anchor": "#4-3-diagnostic-evaluation"
    },
    {
      "level": 4,
      "text": "4.3.1. History",
      "anchor": "#4-3-1-history"
    },
    {
      "level": 4,
      "text": "4.3.2. Physical examination",
      "anchor": "#4-3-2-physical-examination"
    },
    {
      "level": 4,
      "text": "4.3.3. Imaging studies",
      "anchor": "#4-3-3-imaging-studies"
    },
    {
      "level": 3,
      "text": "4.4. Management",
      "anchor": "#4-4-management"
    },
    {
      "level": 4,
      "text": "4.4.1. Medical therapy",
      "anchor": "#4-4-1-medical-therapy"
    },
    {
      "level": 4,
      "text": "4.4.2. Surgical therapy",
      "anchor": "#4-4-2-surgical-therapy"
    },
    {
      "level": 3,
      "text": "4.5. Undescended testes and fertility",
      "anchor": "#4-5-undescended-testes-and-fertility"
    },
    {
      "level": 3,
      "text": "4.6. Undescended testes and malignancy",
      "anchor": "#4-6-undescended-testes-and-malignancy"
    },
    {
      "level": 3,
      "text": "4.7. Summary of evidence and recommendations for the management of undescended testes",
      "anchor": "#4-7-summary-of-evidence-and-recommendations-for-the-management-of-undescended-testes"
    },
    {
      "level": 2,
      "text": "5. TESTICULAR TUMOURS IN PREPUBERTAL BOYS",
      "anchor": "#5-testicular-tumours-in-prepubertal-boys"
    },
    {
      "level": 3,
      "text": "5.1. Epidemiology and pathophysiology",
      "anchor": "#5-1-epidemiology-and-pathophysiology"
    },
    {
      "level": 3,
      "text": "5.2. Clinical presentation",
      "anchor": "#5-2-clinical-presentation"
    },
    {
      "level": 3,
      "text": "5.3. Evaluation",
      "anchor": "#5-3-evaluation"
    },
    {
      "level": 3,
      "text": "5.5. Tumour entities in prepubertal boys",
      "anchor": "#5-5-tumour-entities-in-prepubertal-boys"
    },
    {
      "level": 4,
      "text": "5.5.1. Germ cell tumours",
      "anchor": "#5-5-1-germ-cell-tumours"
    },
    {
      "level": 4,
      "text": "5.5.2. Gonadal stromal tumours",
      "anchor": "#5-5-2-gonadal-stromal-tumours"
    },
    {
      "level": 4,
      "text": "5.5.3. Other tumours",
      "anchor": "#5-5-3-other-tumours"
    },
    {
      "level": 3,
      "text": "5.6. Follow-up",
      "anchor": "#5-6-follow-up"
    },
    {
      "level": 2,
      "text": "6. FERTILITY PRESERVATION IN CHILDREN AND ADOLESCENTS",
      "anchor": "#6-fertility-preservation-in-children-and-adolescents"
    },
    {
      "level": 3,
      "text": "6.1. Ovarian tissue cryopreservation in prepubertal and adolescent girls",
      "anchor": "#6-1-ovarian-tissue-cryopreservation-in-prepubertal-and-adolescent-girls"
    },
    {
      "level": 3,
      "text": "6.2. Cryopreservation in prepubertal and adolescent boys",
      "anchor": "#6-2-cryopreservation-in-prepubertal-and-adolescent-boys"
    },
    {
      "level": 3,
      "text": "6.3. Summary of evidence and recommendations fertility preservation in children and adolescents",
      "anchor": "#6-3-summary-of-evidence-and-recommendations-fertility-preservation-in-children-and-adolescents"
    },
    {
      "level": 2,
      "text": "7. HYDROCELE",
      "anchor": "#7-hydrocele"
    },
    {
      "level": 3,
      "text": "7.1. Epidemiology, aetiology and pathophysiology",
      "anchor": "#7-1-epidemiology-aetiology-and-pathophysiology"
    },
    {
      "level": 3,
      "text": "7.2. Diagnostic evaluation",
      "anchor": "#7-2-diagnostic-evaluation"
    },
    {
      "level": 3,
      "text": "7.3. Management",
      "anchor": "#7-3-management"
    },
    {
      "level": 3,
      "text": "7.4. Summary of evidence and recommendations for the management of hydrocele",
      "anchor": "#7-4-summary-of-evidence-and-recommendations-for-the-management-of-hydrocele"
    },
    {
      "level": 2,
      "text": "8. ACUTE SCROTUM",
      "anchor": "#8-acute-scrotum"
    },
    {
      "level": 3,
      "text": "8.1. Epidemiology, aetiology and pathophysiology",
      "anchor": "#8-1-epidemiology-aetiology-and-pathophysiology"
    },
    {
      "level": 3,
      "text": "8.2. Diagnostic evaluation",
      "anchor": "#8-2-diagnostic-evaluation"
    },
    {
      "level": 3,
      "text": "8.3. Management",
      "anchor": "#8-3-management"
    },
    {
      "level": 4,
      "text": "8.3.1. Epididymitis",
      "anchor": "#8-3-1-epididymitis"
    },
    {
      "level": 4,
      "text": "8.3.2. Testicular torsion",
      "anchor": "#8-3-2-testicular-torsion"
    },
    {
      "level": 4,
      "text": "8.3.3. Surgical treatment",
      "anchor": "#8-3-3-surgical-treatment"
    },
    {
      "level": 3,
      "text": "8.4. Follow-up",
      "anchor": "#8-4-follow-up"
    },
    {
      "level": 4,
      "text": "8.4.1. Fertility",
      "anchor": "#8-4-1-fertility"
    },
    {
      "level": 4,
      "text": "8.4.2. Subfertility",
      "anchor": "#8-4-2-subfertility"
    },
    {
      "level": 4,
      "text": "8.4.3. Androgen levels",
      "anchor": "#8-4-3-androgen-levels"
    },
    {
      "level": 2,
      "text": "9. HYPOSPADIAS",
      "anchor": "#9-hypospadias"
    },
    {
      "level": 3,
      "text": "9.1. Epidemiology, aetiology, and pathophysiology",
      "anchor": "#9-1-epidemiology-aetiology-and-pathophysiology"
    },
    {
      "level": 4,
      "text": "9.1.1. Epidemiology",
      "anchor": "#9-1-1-epidemiology"
    },
    {
      "level": 3,
      "text": "9.2. Risk factors",
      "anchor": "#9-2-risk-factors"
    },
    {
      "level": 3,
      "text": "9.3. Classification systems",
      "anchor": "#9-3-classification-systems"
    },
    {
      "level": 3,
      "text": "9.4. Diagnostic evaluation",
      "anchor": "#9-4-diagnostic-evaluation"
    },
    {
      "level": 3,
      "text": "9.5. Management",
      "anchor": "#9-5-management"
    },
    {
      "level": 4,
      "text": "9.5.1. Indication for reconstruction and therapeutic objectives",
      "anchor": "#9-5-1-indication-for-reconstruction-and-therapeutic-objectives"
    },
    {
      "level": 4,
      "text": "9.5.2. Preoperative hormonal treatment",
      "anchor": "#9-5-2-preoperative-hormonal-treatment"
    },
    {
      "level": 4,
      "text": "9.5.3. Age at surgery",
      "anchor": "#9-5-3-age-at-surgery"
    },
    {
      "level": 4,
      "text": "9.5.4. Penile curvature",
      "anchor": "#9-5-4-penile-curvature"
    },
    {
      "level": 4,
      "text": "9.5.5. Urethral reconstruction",
      "anchor": "#9-5-5-urethral-reconstruction"
    },
    {
      "level": 4,
      "text": "9.5.6. Redo hypospadias repairs",
      "anchor": "#9-5-6-redo-hypospadias-repairs"
    },
    {
      "level": 4,
      "text": "9.5.7. Penile reconstruction following formation of the neo-urethra",
      "anchor": "#9-5-7-penile-reconstruction-following-formation-of-the-neo-urethra"
    },
    {
      "level": 4,
      "text": "9.5.8. Urine drainage and wound dressing",
      "anchor": "#9-5-8-urine-drainage-and-wound-dressing"
    },
    {
      "level": 4,
      "text": "9.5.9. Analgesia (regional blocks)",
      "anchor": "#9-5-9-analgesia-regional-blocks"
    },
    {
      "level": 3,
      "text": "9.6. Outcomes and complications",
      "anchor": "#9-6-outcomes-and-complications"
    },
    {
      "level": 4,
      "text": "9.6.1. Factors influencing outcomes",
      "anchor": "#9-6-1-factors-influencing-outcomes"
    },
    {
      "level": 4,
      "text": "9.6.2. Complications",
      "anchor": "#9-6-2-complications"
    },
    {
      "level": 3,
      "text": "9.7. Long-term follow-up and transition",
      "anchor": "#9-7-long-term-follow-up-and-transition"
    },
    {
      "level": 4,
      "text": "9.7.1. Voiding",
      "anchor": "#9-7-1-voiding"
    },
    {
      "level": 4,
      "text": "9.7.2. Penile appearance",
      "anchor": "#9-7-2-penile-appearance"
    },
    {
      "level": 4,
      "text": "9.7.3. Sexual function and fertility",
      "anchor": "#9-7-3-sexual-function-and-fertility"
    },
    {
      "level": 4,
      "text": "9.7.4. Health-related quality of life",
      "anchor": "#9-7-4-health-related-quality-of-life"
    },
    {
      "level": 4,
      "text": "9.7.5. Transition",
      "anchor": "#9-7-5-transition"
    },
    {
      "level": 3,
      "text": "9.8. Summary of evidence and recommendations for the management of hypospadias",
      "anchor": "#9-8-summary-of-evidence-and-recommendations-for-the-management-of-hypospadias"
    },
    {
      "level": 2,
      "text": "10. CONGENITAL PENILE CURVATURE",
      "anchor": "#10-congenital-penile-curvature"
    },
    {
      "level": 3,
      "text": "10.1. Epidemiology, aetiology and pathophysiology",
      "anchor": "#10-1-epidemiology-aetiology-and-pathophysiology"
    },
    {
      "level": 3,
      "text": "10.2. Diagnostic evaluation",
      "anchor": "#10-2-diagnostic-evaluation"
    },
    {
      "level": 3,
      "text": "10.3. Management",
      "anchor": "#10-3-management"
    },
    {
      "level": 3,
      "text": "10.4. Summary of evidence and recommendations for the management of congenital penile curvature",
      "anchor": "#10-4-summary-of-evidence-and-recommendations-for-the-management-of-congenital-penile-curvature"
    },
    {
      "level": 2,
      "text": "11. VARICOCELE IN CHILDREN AND ADOLESCENTS",
      "anchor": "#11-varicocele-in-children-and-adolescents"
    },
    {
      "level": 3,
      "text": "11.1. Epidemiology, aetiology and pathophysiology",
      "anchor": "#11-1-epidemiology-aetiology-and-pathophysiology"
    },
    {
      "level": 3,
      "text": "11.2. Classification systems",
      "anchor": "#11-2-classification-systems"
    },
    {
      "level": 3,
      "text": "11.3. Diagnostic evaluation",
      "anchor": "#11-3-diagnostic-evaluation"
    },
    {
      "level": 3,
      "text": "11.4. Management",
      "anchor": "#11-4-management"
    },
    {
      "level": 4,
      "text": "11.4.1. Surgical management",
      "anchor": "#11-4-1-surgical-management"
    },
    {
      "level": 4,
      "text": "11.4.2. Radiological management",
      "anchor": "#11-4-2-radiological-management"
    },
    {
      "level": 3,
      "text": "11.5. Summary of evidence and recommendations for the management of varicocele",
      "anchor": "#11-5-summary-of-evidence-and-recommendations-for-the-management-of-varicocele"
    },
    {
      "level": 2,
      "text": "12. URINARY TRACT INFECTIONS IN CHILDREN",
      "anchor": "#12-urinary-tract-infections-in-children"
    },
    {
      "level": 3,
      "text": "12.1. Epidemiology, aetiology and pathophysiology",
      "anchor": "#12-1-epidemiology-aetiology-and-pathophysiology"
    },
    {
      "level": 3,
      "text": "12.2. Presentation symptoms",
      "anchor": "#12-2-presentation-symptoms"
    },
    {
      "level": 3,
      "text": "12.3. Classification systems",
      "anchor": "#12-3-classification-systems"
    },
    {
      "level": 4,
      "text": "12.3.1. Classification according to clinical presentation",
      "anchor": "#12-3-1-classification-according-to-clinical-presentation"
    },
    {
      "level": 4,
      "text": "12.3.2. Classification according to episode: first, recurrent, breakthrough",
      "anchor": "#12-3-2-classification-according-to-episode-first-recurrent-breakthrough"
    },
    {
      "level": 4,
      "text": "12.3.3. Classification according to age and toilet-training status",
      "anchor": "#12-3-3-classification-according-to-age-and-toilet-training-status"
    },
    {
      "level": 4,
      "text": "12.3.4. Classification according to the clinical course",
      "anchor": "#12-3-4-classification-according-to-the-clinical-course"
    },
    {
      "level": 4,
      "text": "12.3.5. Classification according to urinary tract abnormalities",
      "anchor": "#12-3-5-classification-according-to-urinary-tract-abnormalities"
    },
    {
      "level": 3,
      "text": "12.4. Diagnostic evaluation",
      "anchor": "#12-4-diagnostic-evaluation"
    },
    {
      "level": 4,
      "text": "12.4.1. Medical history",
      "anchor": "#12-4-1-medical-history"
    },
    {
      "level": 4,
      "text": "12.4.2. Physical examination",
      "anchor": "#12-4-2-physical-examination"
    },
    {
      "level": 4,
      "text": "12.4.3. Urine sampling, analysis and culture",
      "anchor": "#12-4-3-urine-sampling-analysis-and-culture"
    },
    {
      "level": 4,
      "text": "12.4.4. Blood tests",
      "anchor": "#12-4-4-blood-tests"
    },
    {
      "level": 3,
      "text": "12.5. Additional workup",
      "anchor": "#12-5-additional-workup"
    },
    {
      "level": 4,
      "text": "12.5.1. Ultrasound (US)",
      "anchor": "#12-5-1-ultrasound-us"
    },
    {
      "level": 3,
      "text": "12.6. Management",
      "anchor": "#12-6-management"
    },
    {
      "level": 4,
      "text": "12.6.1. Administration route of antibacterial therapy",
      "anchor": "#12-6-1-administration-route-of-antibacterial-therapy"
    },
    {
      "level": 4,
      "text": "12.6.2. Adjustment of antimicrobial agents",
      "anchor": "#12-6-2-adjustment-of-antimicrobial-agents"
    },
    {
      "level": 4,
      "text": "12.6.3. Duration of therapy",
      "anchor": "#12-6-3-duration-of-therapy"
    },
    {
      "level": 4,
      "text": "12.6.4. Adjunct steroid treatment",
      "anchor": "#12-6-4-adjunct-steroid-treatment"
    },
    {
      "level": 4,
      "text": "12.6.5. Temporary urinary diversion",
      "anchor": "#12-6-5-temporary-urinary-diversion"
    },
    {
      "level": 4,
      "text": "12.6.6. Monitoring",
      "anchor": "#12-6-6-monitoring"
    },
    {
      "level": 3,
      "text": "12.7. Measures to prevent UTI recurrences",
      "anchor": "#12-7-measures-to-prevent-uti-recurrences"
    },
    {
      "level": 4,
      "text": "12.7.1. Chemoprophylaxis",
      "anchor": "#12-7-1-chemoprophylaxis"
    },
    {
      "level": 4,
      "text": "12.7.2. Nonantibiotic prophylaxis",
      "anchor": "#12-7-2-nonantibiotic-prophylaxis"
    },
    {
      "level": 4,
      "text": "12.7.3. Phimosis",
      "anchor": "#12-7-3-phimosis"
    },
    {
      "level": 4,
      "text": "12.7.4. Bladder and bowel dysfunction and lower urinary tract disorders",
      "anchor": "#12-7-4-bladder-and-bowel-dysfunction-and-lower-urinary-tract-disorders"
    },
    {
      "level": 3,
      "text": "12.8. Summary of evidence and recommendations for the management of UTI in children",
      "anchor": "#12-8-summary-of-evidence-and-recommendations-for-the-management-of-uti-in-children"
    },
    {
      "level": 2,
      "text": "13. DAYTIME LOWER URINARY TRACT CONDITIONS",
      "anchor": "#13-daytime-lower-urinary-tract-conditions"
    },
    {
      "level": 3,
      "text": "13.1. Terminology, classification, epidemiology and pathophysiology",
      "anchor": "#13-1-terminology-classification-epidemiology-and-pathophysiology"
    },
    {
      "level": 4,
      "text": "13.1.1. Filling-phase (storage) dysfunctions",
      "anchor": "#13-1-1-filling-phase-storage-dysfunctions"
    },
    {
      "level": 4,
      "text": "13.1.2. Voiding-phase (emptying) dysfunctions",
      "anchor": "#13-1-2-voiding-phase-emptying-dysfunctions"
    },
    {
      "level": 3,
      "text": "13.2. Diagnostic evaluation",
      "anchor": "#13-2-diagnostic-evaluation"
    },
    {
      "level": 4,
      "text": "13.2.1. History and physical examination",
      "anchor": "#13-2-1-history-and-physical-examination"
    },
    {
      "level": 4,
      "text": "13.2.2. Ultrasound and urinalysis",
      "anchor": "#13-2-2-ultrasound-and-urinalysis"
    },
    {
      "level": 4,
      "text": "13.2.3. Urodynamics",
      "anchor": "#13-2-3-urodynamics"
    },
    {
      "level": 3,
      "text": "13.3. Management",
      "anchor": "#13-3-management"
    },
    {
      "level": 4,
      "text": "13.3.1. Urotherapy and specific add-on interventions",
      "anchor": "#13-3-1-urotherapy-and-specific-add-on-interventions"
    },
    {
      "level": 4,
      "text": "13.3.2. Medication",
      "anchor": "#13-3-2-medication"
    },
    {
      "level": 4,
      "text": "13.3.3. Neuromodulation",
      "anchor": "#13-3-3-neuromodulation"
    },
    {
      "level": 4,
      "text": "13.3.4. Surgery",
      "anchor": "#13-3-4-surgery"
    },
    {
      "level": 3,
      "text": "13.4. Quality of life",
      "anchor": "#13-4-quality-of-life"
    },
    {
      "level": 3,
      "text": "13.5. Follow-up",
      "anchor": "#13-5-follow-up"
    },
    {
      "level": 3,
      "text": "13.6. Summary of evidence and recommendations for the management of daytime lower urinary tract conditions",
      "anchor": "#13-6-summary-of-evidence-and-recommendations-for-the-management-of-daytime-lower-urinary-tract-conditions"
    },
    {
      "level": 2,
      "text": "14. MONOSYMPTOMATIC NOCTURNAL ENURESIS - BEDWETTING",
      "anchor": "#14-monosymptomatic-nocturnal-enuresis---bedwetting"
    },
    {
      "level": 3,
      "text": "14.1. Epidemiology, aetiology and pathophysiology",
      "anchor": "#14-1-epidemiology-aetiology-and-pathophysiology"
    },
    {
      "level": 3,
      "text": "14.2. Diagnostic evaluation",
      "anchor": "#14-2-diagnostic-evaluation"
    },
    {
      "level": 3,
      "text": "14.3. Management",
      "anchor": "#14-3-management"
    },
    {
      "level": 4,
      "text": "14.3.1. Supportive treatment measures",
      "anchor": "#14-3-1-supportive-treatment-measures"
    },
    {
      "level": 4,
      "text": "14.3.2. Wetting alarm treatment",
      "anchor": "#14-3-2-wetting-alarm-treatment"
    },
    {
      "level": 4,
      "text": "14.3.3. Medical treatment",
      "anchor": "#14-3-3-medical-treatment"
    },
    {
      "level": 4,
      "text": "14.3.4. Electrical neuromodulation",
      "anchor": "#14-3-4-electrical-neuromodulation"
    },
    {
      "level": 4,
      "text": "14.3.5. Complementary treatments:",
      "anchor": "#14-3-5-complementary-treatments"
    },
    {
      "level": 4,
      "text": "14.3.6. Conservative ‘wait-and-see’ approach",
      "anchor": "#14-3-6-conservative-wait-and-see-approach"
    },
    {
      "level": 3,
      "text": "14.4. Summary of evidence and recommendations for the management of monosymptomatic enuresis",
      "anchor": "#14-4-summary-of-evidence-and-recommendations-for-the-management-of-monosymptomatic-enuresis"
    },
    {
      "level": 2,
      "text": "15. SPINAL DYSRAPHISM IN CHILDREN AND ADOLESCENTS (FORMALLY NEUROGENIC BLADDER)",
      "anchor": "#15-spinal-dysraphism-in-children-and-adolescents-formally-neurogenic-bladder"
    },
    {
      "level": 2,
      "text": "16. DILATATION OF THE UPPER URINARY TRACT (PUJ OBSTRUCTION)",
      "anchor": "#16-dilatation-of-the-upper-urinary-tract-puj-obstruction"
    },
    {
      "level": 3,
      "text": "16.1. Epidemiology, aetiology and pathophysiology",
      "anchor": "#16-1-epidemiology-aetiology-and-pathophysiology"
    },
    {
      "level": 3,
      "text": "16.2. Diagnostic evaluation",
      "anchor": "#16-2-diagnostic-evaluation"
    },
    {
      "level": 4,
      "text": "16.2.1. Antenatal ultrasound",
      "anchor": "#16-2-1-antenatal-ultrasound"
    },
    {
      "level": 4,
      "text": "16.2.2. Postnatal ultrasound",
      "anchor": "#16-2-2-postnatal-ultrasound"
    },
    {
      "level": 4,
      "text": "16.2.3. Voiding cystourethrogram",
      "anchor": "#16-2-3-voiding-cystourethrogram"
    },
    {
      "level": 4,
      "text": "16.2.4. Diuretic renography",
      "anchor": "#16-2-4-diuretic-renography"
    },
    {
      "level": 4,
      "text": "16.2.5. Severity classification and risk stratification",
      "anchor": "#16-2-5-severity-classification-and-risk-stratification"
    },
    {
      "level": 4,
      "text": "16.2.6. Biomarkers",
      "anchor": "#16-2-6-biomarkers"
    },
    {
      "level": 3,
      "text": "16.3. Management",
      "anchor": "#16-3-management"
    },
    {
      "level": 4,
      "text": "16.3.1. Prenatal management",
      "anchor": "#16-3-1-prenatal-management"
    },
    {
      "level": 4,
      "text": "16.3.2. PUJ obstruction",
      "anchor": "#16-3-2-puj-obstruction"
    },
    {
      "level": 3,
      "text": "16.4. Summary of evidence and recommendations for the management of PUJ obstruction",
      "anchor": "#16-4-summary-of-evidence-and-recommendations-for-the-management-of-puj-obstruction"
    },
    {
      "level": 2,
      "text": "17. VESICOURETERIC REFLUX",
      "anchor": "#17-vesicoureteric-reflux"
    },
    {
      "level": 3,
      "text": "17.1. Epidemiology, aetiology and pathophysiology",
      "anchor": "#17-1-epidemiology-aetiology-and-pathophysiology"
    },
    {
      "level": 3,
      "text": "17.2. Diagnostic evaluation",
      "anchor": "#17-2-diagnostic-evaluation"
    },
    {
      "level": 4,
      "text": "17.2.1. Recommendation for diagnosis of VUR",
      "anchor": "#17-2-1-recommendation-for-diagnosis-of-vur"
    },
    {
      "level": 4,
      "text": "17.2.2. Infants presenting with prenatally diagnosed hydronephrosis",
      "anchor": "#17-2-2-infants-presenting-with-prenatally-diagnosed-hydronephrosis"
    },
    {
      "level": 4,
      "text": "17.2.3. Siblings and offspring of reflux patients",
      "anchor": "#17-2-3-siblings-and-offspring-of-reflux-patients"
    },
    {
      "level": 4,
      "text": "17.2.4. Recommendation for paediatric screening of VUR",
      "anchor": "#17-2-4-recommendation-for-paediatric-screening-of-vur"
    },
    {
      "level": 4,
      "text": "17.2.5. Children with febrile urinary tract infections",
      "anchor": "#17-2-5-children-with-febrile-urinary-tract-infections"
    },
    {
      "level": 4,
      "text": "17.2.6. Children with lower urinary tract symptoms and vesicoureteric reflux",
      "anchor": "#17-2-6-children-with-lower-urinary-tract-symptoms-and-vesicoureteric-reflux"
    },
    {
      "level": 3,
      "text": "17.3. Disease management",
      "anchor": "#17-3-disease-management"
    },
    {
      "level": 4,
      "text": "17.3.1. Nonsurgical therapy",
      "anchor": "#17-3-1-nonsurgical-therapy"
    },
    {
      "level": 4,
      "text": "17.3.2. Surgical treatment",
      "anchor": "#17-3-2-surgical-treatment"
    },
    {
      "level": 3,
      "text": "17.4. Summary of evidence and recommendations for the management of vesicoureteric reflux in childhood",
      "anchor": "#17-4-summary-of-evidence-and-recommendations-for-the-management-of-vesicoureteric-reflux-in-childhood"
    },
    {
      "level": 2,
      "text": "18. URINARY STONE DISEASE",
      "anchor": "#18-urinary-stone-disease"
    },
    {
      "level": 3,
      "text": "18.1. Epidemiology, aetiology and pathophysiology",
      "anchor": "#18-1-epidemiology-aetiology-and-pathophysiology"
    },
    {
      "level": 3,
      "text": "18.2. Classification systems",
      "anchor": "#18-2-classification-systems"
    },
    {
      "level": 4,
      "text": "18.2.1. Calcium stones",
      "anchor": "#18-2-1-calcium-stones"
    },
    {
      "level": 4,
      "text": "18.2.2. Uric acid stones",
      "anchor": "#18-2-2-uric-acid-stones"
    },
    {
      "level": 4,
      "text": "18.2.3. Cystine stones",
      "anchor": "#18-2-3-cystine-stones"
    },
    {
      "level": 4,
      "text": "18.2.4. Infection stones (struvite stones)",
      "anchor": "#18-2-4-infection-stones-struvite-stones"
    },
    {
      "level": 3,
      "text": "18.3. Diagnostic evaluation",
      "anchor": "#18-3-diagnostic-evaluation"
    },
    {
      "level": 4,
      "text": "18.3.1. Imaging",
      "anchor": "#18-3-1-imaging"
    },
    {
      "level": 4,
      "text": "18.3.2. Metabolic evaluation",
      "anchor": "#18-3-2-metabolic-evaluation"
    },
    {
      "level": 4,
      "text": "18.3.3. Urolithiasis in infants",
      "anchor": "#18-3-3-urolithiasis-in-infants"
    },
    {
      "level": 3,
      "text": "18.4. Management",
      "anchor": "#18-4-management"
    },
    {
      "level": 4,
      "text": "18.4.1. Extracorporeal shockwave lithotripsy",
      "anchor": "#18-4-1-extracorporeal-shockwave-lithotripsy"
    },
    {
      "level": 4,
      "text": "18.4.2. Percutaneous nephrolithotomy",
      "anchor": "#18-4-2-percutaneous-nephrolithotomy"
    },
    {
      "level": 4,
      "text": "18.4.3. Ureterorenoscopy",
      "anchor": "#18-4-3-ureterorenoscopy"
    },
    {
      "level": 4,
      "text": "18.4.4. Open or laparoscopic stone surgery",
      "anchor": "#18-4-4-open-or-laparoscopic-stone-surgery"
    },
    {
      "level": 3,
      "text": "18.5. Summary of evidence and recommendations for the management of urinary stones",
      "anchor": "#18-5-summary-of-evidence-and-recommendations-for-the-management-of-urinary-stones"
    },
    {
      "level": 2,
      "text": "19. URETEROCELE AND ECTOPIC URETER",
      "anchor": "#19-ureterocele-and-ectopic-ureter"
    },
    {
      "level": 3,
      "text": "19.1. Ureterocele",
      "anchor": "#19-1-ureterocele"
    },
    {
      "level": 4,
      "text": "19.1.1. Epidemiology, aetiology and pathophysiology",
      "anchor": "#19-1-1-epidemiology-aetiology-and-pathophysiology"
    },
    {
      "level": 4,
      "text": "19.1.2. Classification systems",
      "anchor": "#19-1-2-classification-systems"
    },
    {
      "level": 4,
      "text": "19.1.3. Diagnostic evaluation",
      "anchor": "#19-1-3-diagnostic-evaluation"
    },
    {
      "level": 4,
      "text": "19.1.4. Management",
      "anchor": "#19-1-4-management"
    },
    {
      "level": 3,
      "text": "19.2. Ectopic ureter",
      "anchor": "#19-2-ectopic-ureter"
    },
    {
      "level": 4,
      "text": "19.2.1. Epidemiology, aetiology and pathophysiology",
      "anchor": "#19-2-1-epidemiology-aetiology-and-pathophysiology"
    },
    {
      "level": 4,
      "text": "19.2.2. Classification",
      "anchor": "#19-2-2-classification"
    },
    {
      "level": 4,
      "text": "19.2.3. Clinical presentation and diagnostic evaluation",
      "anchor": "#19-2-3-clinical-presentation-and-diagnostic-evaluation"
    },
    {
      "level": 4,
      "text": "19.2.4. Management",
      "anchor": "#19-2-4-management"
    },
    {
      "level": 3,
      "text": "19.3. Summary of evidence and recommendations for the management of obstructive pathology of renal duplication: ureterocele and ectopic ureter",
      "anchor": "#19-3-summary-of-evidence-and-recommendations-for-the-management-of-obstructive-pathology-of-renal-duplication-ureterocele-and-ectopic-ureter"
    },
    {
      "level": 3,
      "text": "20.1. Introduction",
      "anchor": "#20-1-introduction"
    },
    {
      "level": 3,
      "text": "20.2. International consensus statements on DSD management",
      "anchor": "#20-2-international-consensus-statements-on-dsd-management"
    },
    {
      "level": 3,
      "text": "20.3. Current classification of DSD conditions",
      "anchor": "#20-3-current-classification-of-dsd-conditions"
    },
    {
      "level": 3,
      "text": "20.4. Diagnostic evaluation",
      "anchor": "#20-4-diagnostic-evaluation"
    },
    {
      "level": 4,
      "text": "20.4.1. The neonatal emergency",
      "anchor": "#20-4-1-the-neonatal-emergency"
    },
    {
      "level": 4,
      "text": "20.4.2. Family history and clinical examination",
      "anchor": "#20-4-2-family-history-and-clinical-examination"
    },
    {
      "level": 3,
      "text": "20.5. Gender assignment",
      "anchor": "#20-5-gender-assignment"
    },
    {
      "level": 3,
      "text": "20.6. Risk of tumour development",
      "anchor": "#20-6-risk-of-tumour-development"
    },
    {
      "level": 3,
      "text": "20.7. Quality of life",
      "anchor": "#20-7-quality-of-life"
    },
    {
      "level": 2,
      "text": "21. CONGENITAL LOWER URINARY TRACT OBSTRUCTION",
      "anchor": "#21-congenital-lower-urinary-tract-obstruction"
    },
    {
      "level": 3,
      "text": "21.1. Epidemiology and pathophysiology",
      "anchor": "#21-1-epidemiology-and-pathophysiology"
    },
    {
      "level": 3,
      "text": "21.2. Classification systems of the urethral valves",
      "anchor": "#21-2-classification-systems-of-the-urethral-valves"
    },
    {
      "level": 3,
      "text": "21.3. Diagnostic evaluation",
      "anchor": "#21-3-diagnostic-evaluation"
    },
    {
      "level": 3,
      "text": "21.4. Management",
      "anchor": "#21-4-management"
    },
    {
      "level": 4,
      "text": "21.4.1. Prenatal treatment",
      "anchor": "#21-4-1-prenatal-treatment"
    },
    {
      "level": 4,
      "text": "21.4.2. Postnatal treatment",
      "anchor": "#21-4-2-postnatal-treatment"
    },
    {
      "level": 3,
      "text": "21.5. Follow-up",
      "anchor": "#21-5-follow-up"
    },
    {
      "level": 3,
      "text": "21.6. Summary of evidence and recommendations for the management of posterior urethral valves",
      "anchor": "#21-6-summary-of-evidence-and-recommendations-for-the-management-of-posterior-urethral-valves"
    },
    {
      "level": 2,
      "text": "22. RARE CONDITIONS IN CHILDHOOD",
      "anchor": "#22-rare-conditions-in-childhood"
    },
    {
      "level": 3,
      "text": "22.1. Urachal remnants",
      "anchor": "#22-1-urachal-remnants"
    },
    {
      "level": 4,
      "text": "22.1.1. Introduction",
      "anchor": "#22-1-1-introduction"
    },
    {
      "level": 4,
      "text": "22.1.2. Epidemiology",
      "anchor": "#22-1-2-epidemiology"
    },
    {
      "level": 4,
      "text": "22.1.3. Symptoms",
      "anchor": "#22-1-3-symptoms"
    },
    {
      "level": 4,
      "text": "22.1.4. Diagnosis",
      "anchor": "#22-1-4-diagnosis"
    },
    {
      "level": 4,
      "text": "22.1.5. Treatment",
      "anchor": "#22-1-5-treatment"
    },
    {
      "level": 4,
      "text": "22.1.6. Pathology of removed remnants",
      "anchor": "#22-1-6-pathology-of-removed-remnants"
    },
    {
      "level": 4,
      "text": "22.1.7. Urachal cancer",
      "anchor": "#22-1-7-urachal-cancer"
    },
    {
      "level": 4,
      "text": "22.1.8. Summary of evidence and recommendation for management of urachal remnants",
      "anchor": "#22-1-8-summary-of-evidence-and-recommendation-for-management-of-urachal-remnants"
    },
    {
      "level": 3,
      "text": "22.2. Papillary tumours of the bladder in children and adolescents (Papillary urothelial neoplasm of low malignant potential)",
      "anchor": "#22-2-papillary-tumours-of-the-bladder-in-children-and-adolescents-papillary-urothelial-neoplasm-of-low-malignant-potential"
    },
    {
      "level": 4,
      "text": "22.2.1. Incidence",
      "anchor": "#22-2-1-incidence"
    },
    {
      "level": 4,
      "text": "22.2.2. Differences and similarities of papillary tumours of the bladder in children and adults",
      "anchor": "#22-2-2-differences-and-similarities-of-papillary-tumours-of-the-bladder-in-children-and-adults"
    },
    {
      "level": 4,
      "text": "22.2.3. Risk factors",
      "anchor": "#22-2-3-risk-factors"
    },
    {
      "level": 4,
      "text": "22.2.4. Presentation",
      "anchor": "#22-2-4-presentation"
    },
    {
      "level": 4,
      "text": "22.2.5. Investigations and treatment",
      "anchor": "#22-2-5-investigations-and-treatment"
    },
    {
      "level": 4,
      "text": "22.2.6. Histology",
      "anchor": "#22-2-6-histology"
    },
    {
      "level": 4,
      "text": "22.2.7. Additional treatment",
      "anchor": "#22-2-7-additional-treatment"
    },
    {
      "level": 4,
      "text": "22.2.8. Prognosis, recurrence and surveillance",
      "anchor": "#22-2-8-prognosis-recurrence-and-surveillance"
    },
    {
      "level": 4,
      "text": "22.2.9. Summary of evidence and recommendations for papillary tumours of the bladder in children",
      "anchor": "#22-2-9-summary-of-evidence-and-recommendations-for-papillary-tumours-of-the-bladder-in-children"
    },
    {
      "level": 3,
      "text": "22.3. Penile rare conditions",
      "anchor": "#22-3-penile-rare-conditions"
    },
    {
      "level": 4,
      "text": "22.3.1. Cystic lesions",
      "anchor": "#22-3-1-cystic-lesions"
    },
    {
      "level": 4,
      "text": "22.3.2. Vascular malformations",
      "anchor": "#22-3-2-vascular-malformations"
    },
    {
      "level": 4,
      "text": "22.3.3. Neurogenic lesions",
      "anchor": "#22-3-3-neurogenic-lesions"
    },
    {
      "level": 4,
      "text": "22.3.4. Soft tissue tumours of penis",
      "anchor": "#22-3-4-soft-tissue-tumours-of-penis"
    },
    {
      "level": 4,
      "text": "22.3.5. Penile lymphedema",
      "anchor": "#22-3-5-penile-lymphedema"
    },
    {
      "level": 2,
      "text": "23. EMERGENCIES IN PAEDIATRIC UROLOGY",
      "anchor": "#23-emergencies-in-paediatric-urology"
    },
    {
      "level": 3,
      "text": "23.1. Acute scrotum",
      "anchor": "#23-1-acute-scrotum"
    },
    {
      "level": 3,
      "text": "23.2. Paraphimosis",
      "anchor": "#23-2-paraphimosis"
    },
    {
      "level": 3,
      "text": "23.3. Priapism",
      "anchor": "#23-3-priapism"
    },
    {
      "level": 4,
      "text": "23.3.1. Epidemiology, aetiology and pathophysiology",
      "anchor": "#23-3-1-epidemiology-aetiology-and-pathophysiology"
    },
    {
      "level": 4,
      "text": "23.3.2. Classification",
      "anchor": "#23-3-2-classification"
    },
    {
      "level": 4,
      "text": "23.3.3. Diagnostic evaluation",
      "anchor": "#23-3-3-diagnostic-evaluation"
    },
    {
      "level": 4,
      "text": "23.3.4. Disease management",
      "anchor": "#23-3-4-disease-management"
    },
    {
      "level": 3,
      "text": "23.4. Summary of evidence and recommendations for the diagnosis and management of priapism",
      "anchor": "#23-4-summary-of-evidence-and-recommendations-for-the-diagnosis-and-management-of-priapism"
    },
    {
      "level": 2,
      "text": "24. PAEDIATRIC UROLOGICAL TRAUMA",
      "anchor": "#24-paediatric-urological-trauma"
    },
    {
      "level": 3,
      "text": "24.1. Paediatric renal trauma",
      "anchor": "#24-1-paediatric-renal-trauma"
    },
    {
      "level": 4,
      "text": "24.1.1. Epidemiology, aetiology and pathophysiology",
      "anchor": "#24-1-1-epidemiology-aetiology-and-pathophysiology"
    },
    {
      "level": 4,
      "text": "24.1.2. Classification systems",
      "anchor": "#24-1-2-classification-systems"
    },
    {
      "level": 4,
      "text": "24.1.3. Diagnostic evaluation",
      "anchor": "#24-1-3-diagnostic-evaluation"
    },
    {
      "level": 4,
      "text": "24.1.4. Disease management",
      "anchor": "#24-1-4-disease-management"
    },
    {
      "level": 4,
      "text": "24.1.5. Recommendations for the diagnosis and management of paediatric renal trauma",
      "anchor": "#24-1-5-recommendations-for-the-diagnosis-and-management-of-paediatric-renal-trauma"
    },
    {
      "level": 3,
      "text": "24.2. Paediatric ureteral trauma",
      "anchor": "#24-2-paediatric-ureteral-trauma"
    },
    {
      "level": 4,
      "text": "24.2.1. Diagnostic evaluation",
      "anchor": "#24-2-1-diagnostic-evaluation"
    },
    {
      "level": 4,
      "text": "24.2.2. Management",
      "anchor": "#24-2-2-management"
    },
    {
      "level": 4,
      "text": "24.2.3. Recommendations for the diagnosis and management of paediatric ureteral trauma",
      "anchor": "#24-2-3-recommendations-for-the-diagnosis-and-management-of-paediatric-ureteral-trauma"
    },
    {
      "level": 3,
      "text": "24.3. Paediatric bladder injuries",
      "anchor": "#24-3-paediatric-bladder-injuries"
    },
    {
      "level": 4,
      "text": "24.3.1. Diagnostic evaluation",
      "anchor": "#24-3-1-diagnostic-evaluation"
    },
    {
      "level": 4,
      "text": "24.3.2. Management",
      "anchor": "#24-3-2-management"
    },
    {
      "level": 4,
      "text": "24.3.3. Recommendations for the diagnosis and management of paediatric bladder injuries",
      "anchor": "#24-3-3-recommendations-for-the-diagnosis-and-management-of-paediatric-bladder-injuries"
    },
    {
      "level": 3,
      "text": "24.4. Paediatric urethral injuries",
      "anchor": "#24-4-paediatric-urethral-injuries"
    },
    {
      "level": 4,
      "text": "24.4.1. Diagnostic evaluation",
      "anchor": "#24-4-1-diagnostic-evaluation"
    },
    {
      "level": 4,
      "text": "24.4.2. Disease management",
      "anchor": "#24-4-2-disease-management"
    },
    {
      "level": 4,
      "text": "24.4.3. Recommendations for the diagnosis and management of paediatric trauma",
      "anchor": "#24-4-3-recommendations-for-the-diagnosis-and-management-of-paediatric-trauma"
    },
    {
      "level": 3,
      "text": "24.5. Urosepsis",
      "anchor": "#24-5-urosepsis"
    },
    {
      "level": 2,
      "text": "25. PERIOPERATIVE MANAGEMENT",
      "anchor": "#25-perioperative-management"
    },
    {
      "level": 3,
      "text": "25.1. Preoperative fasting, intraoperative fluid therapy, postoperative feeding, fasting and fluid management",
      "anchor": "#25-1-preoperative-fasting-intraoperative-fluid-therapy-postoperative-feeding-fasting-and-fluid-management"
    },
    {
      "level": 4,
      "text": "25.1.1. Epidemiology, aetiology and pathophysiology",
      "anchor": "#25-1-1-epidemiology-aetiology-and-pathophysiology"
    },
    {
      "level": 4,
      "text": "25.1.2. Disease management",
      "anchor": "#25-1-2-disease-management"
    },
    {
      "level": 4,
      "text": "25.1.3. Summary of evidence and recommendations for the management of perioperative fluid management",
      "anchor": "#25-1-3-summary-of-evidence-and-recommendations-for-the-management-of-perioperative-fluid-management"
    },
    {
      "level": 3,
      "text": "25.2. Postoperative pain management: general information",
      "anchor": "#25-2-postoperative-pain-management-general-information"
    },
    {
      "level": 4,
      "text": "25.2.1. Epidemiology, aetiology and pathophysiology",
      "anchor": "#25-2-1-epidemiology-aetiology-and-pathophysiology"
    },
    {
      "level": 4,
      "text": "25.2.2. Diagnostic evaluation",
      "anchor": "#25-2-2-diagnostic-evaluation"
    },
    {
      "level": 4,
      "text": "25.2.3. Disease management",
      "anchor": "#25-2-3-disease-management"
    },
    {
      "level": 4,
      "text": "25.2.4. Summary of evidence and recommendations for the management of post-operative pain",
      "anchor": "#25-2-4-summary-of-evidence-and-recommendations-for-the-management-of-post-operative-pain"
    },
    {
      "level": 3,
      "text": "25.3. Antibiotics management: general information",
      "anchor": "#25-3-antibiotics-management-general-information"
    },
    {
      "level": 3,
      "text": "25.4. Thromboprophylaxis management: general information",
      "anchor": "#25-4-thromboprophylaxis-management-general-information"
    },
    {
      "level": 4,
      "text": "25.4.1. Epidemiology, aetiology, pathophysiology",
      "anchor": "#25-4-1-epidemiology-aetiology-pathophysiology"
    },
    {
      "level": 4,
      "text": "25.4.2. Diagnostic evaluation",
      "anchor": "#25-4-2-diagnostic-evaluation"
    },
    {
      "level": 4,
      "text": "25.4.3. Disease management",
      "anchor": "#25-4-3-disease-management"
    },
    {
      "level": 4,
      "text": "25.4.4. Pharmacological treatment for thromboprophylaxis",
      "anchor": "#25-4-4-pharmacological-treatment-for-thromboprophylaxis"
    },
    {
      "level": 4,
      "text": "25.4.5. Prevention of CVL-related VTE",
      "anchor": "#25-4-5-prevention-of-cvl-related-vte"
    },
    {
      "level": 4,
      "text": "25.4.6. Summary of evidence and recommendations for the management of thromboprophylaxis management",
      "anchor": "#25-4-6-summary-of-evidence-and-recommendations-for-the-management-of-thromboprophylaxis-management"
    },
    {
      "level": 3,
      "text": "25.5. Premedication management: general information",
      "anchor": "#25-5-premedication-management-general-information"
    },
    {
      "level": 4,
      "text": "25.5.1. Recommendations for premedication management: general recommendations",
      "anchor": "#25-5-1-recommendations-for-premedication-management-general-recommendations"
    },
    {
      "level": 2,
      "text": "26. BASIC PRINCIPLES OF LAPAROSCOPIC SURGERY IN CHILDREN",
      "anchor": "#26-basic-principles-of-laparoscopic-surgery-in-children"
    },
    {
      "level": 3,
      "text": "26.1. Epidemiology, aetiology and pathophysiology",
      "anchor": "#26-1-epidemiology-aetiology-and-pathophysiology"
    },
    {
      "level": 3,
      "text": "26.2. Technical considerations and physiological consequences",
      "anchor": "#26-2-technical-considerations-and-physiological-consequences"
    },
    {
      "level": 4,
      "text": "26.2.1. Preoperative evaluation",
      "anchor": "#26-2-1-preoperative-evaluation"
    },
    {
      "level": 4,
      "text": "26.2.2. Abdominal insufflation",
      "anchor": "#26-2-2-abdominal-insufflation"
    },
    {
      "level": 4,
      "text": "26.2.3. Pulmonary effects",
      "anchor": "#26-2-3-pulmonary-effects"
    },
    {
      "level": 4,
      "text": "26.2.4. Cardiovascular effects",
      "anchor": "#26-2-4-cardiovascular-effects"
    },
    {
      "level": 4,
      "text": "26.2.5. Effects on renal function",
      "anchor": "#26-2-5-effects-on-renal-function"
    },
    {
      "level": 4,
      "text": "26.2.6. Effects on neurological system",
      "anchor": "#26-2-6-effects-on-neurological-system"
    },
    {
      "level": 4,
      "text": "26.2.7. Comparison of robot-assisted laparoscopic surgery versus laparoscopic surgery",
      "anchor": "#26-2-7-comparison-of-robot-assisted-laparoscopic-surgery-versus-laparoscopic-surgery"
    },
    {
      "level": 3,
      "text": "26.3. Summary of evidence and recommendations for laparoscopy in children",
      "anchor": "#26-3-summary-of-evidence-and-recommendations-for-laparoscopy-in-children"
    },
    {
      "level": 2,
      "text": "27. TRANSITIONAL UROLOGY",
      "anchor": "#27-transitional-urology"
    },
    {
      "level": 3,
      "text": "27.1. Introduction",
      "anchor": "#27-1-introduction"
    },
    {
      "level": 3,
      "text": "27.2. Barriers in transition",
      "anchor": "#27-2-barriers-in-transition"
    },
    {
      "level": 3,
      "text": "27.3. The transition process",
      "anchor": "#27-3-the-transition-process"
    },
    {
      "level": 3,
      "text": "27.4. Specific genitourinary conditions",
      "anchor": "#27-4-specific-genitourinary-conditions"
    },
    {
      "level": 4,
      "text": "27.4.1. Neurogenic bladder",
      "anchor": "#27-4-1-neurogenic-bladder"
    },
    {
      "level": 4,
      "text": "27.4.2. Posterior urethral valves",
      "anchor": "#27-4-2-posterior-urethral-valves"
    },
    {
      "level": 4,
      "text": "27.4.3. Hypospadias",
      "anchor": "#27-4-3-hypospadias"
    },
    {
      "level": 4,
      "text": "27.4.4. Bladder-exstrophy-epispadias complex",
      "anchor": "#27-4-4-bladder-exstrophy-epispadias-complex"
    },
    {
      "level": 4,
      "text": "27.4.5. Differences of sex development",
      "anchor": "#27-4-5-differences-of-sex-development"
    },
    {
      "level": 3,
      "text": "27.5. Summary of evidence and recommendations for transitional urology",
      "anchor": "#27-5-summary-of-evidence-and-recommendations-for-transitional-urology"
    },
    {
      "level": 2,
      "text": "28. FOETAL UROLOGY",
      "anchor": "#28-foetal-urology"
    },
    {
      "level": 3,
      "text": "28.1. Normal renal development",
      "anchor": "#28-1-normal-renal-development"
    },
    {
      "level": 4,
      "text": "28.1.1. Introduction",
      "anchor": "#28-1-1-introduction"
    },
    {
      "level": 4,
      "text": "28.1.2. Renal and bladder development",
      "anchor": "#28-1-2-renal-and-bladder-development"
    },
    {
      "level": 3,
      "text": "28.2. Antenatal hydronephrosis",
      "anchor": "#28-2-antenatal-hydronephrosis"
    },
    {
      "level": 4,
      "text": "28.2.1. Definitions and follow-up during pregnancy",
      "anchor": "#28-2-1-definitions-and-follow-up-during-pregnancy"
    },
    {
      "level": 4,
      "text": "28.2.2. Aetiology",
      "anchor": "#28-2-2-aetiology"
    },
    {
      "level": 4,
      "text": "28.2.3. Classification systems for postnatal outcomes",
      "anchor": "#28-2-3-classification-systems-for-postnatal-outcomes"
    },
    {
      "level": 4,
      "text": "28.2.4. Postnatal outcomes",
      "anchor": "#28-2-4-postnatal-outcomes"
    },
    {
      "level": 4,
      "text": "28.2.5. Long-term outcomes",
      "anchor": "#28-2-5-long-term-outcomes"
    },
    {
      "level": 4,
      "text": "28.2.6. Prophylactic measures against UTIs",
      "anchor": "#28-2-6-prophylactic-measures-against-utis"
    },
    {
      "level": 3,
      "text": "28.3. Congenital lower urinary tract obstruction",
      "anchor": "#28-3-congenital-lower-urinary-tract-obstruction"
    },
    {
      "level": 4,
      "text": "28.3.1. Introduction",
      "anchor": "#28-3-1-introduction"
    },
    {
      "level": 4,
      "text": "28.3.2. Diagnosis",
      "anchor": "#28-3-2-diagnosis"
    },
    {
      "level": 4,
      "text": "28.3.3. Management",
      "anchor": "#28-3-3-management"
    },
    {
      "level": 4,
      "text": "28.3.4. Foetal cystoscopy",
      "anchor": "#28-3-4-foetal-cystoscopy"
    },
    {
      "level": 4,
      "text": "28.3.5. Serial amniotic infusions",
      "anchor": "#28-3-5-serial-amniotic-infusions"
    },
    {
      "level": 4,
      "text": "28.3.6. Outcomes postnatally",
      "anchor": "#28-3-6-outcomes-postnatally"
    },
    {
      "level": 4,
      "text": "28.3.7. Postnatal management",
      "anchor": "#28-3-7-postnatal-management"
    },
    {
      "level": 4,
      "text": "28.3.8. Complex urogenital pathologies - prenatal management and considerations",
      "anchor": "#28-3-8-complex-urogenital-pathologies---prenatal-management-and-considerations"
    },
    {
      "level": 4,
      "text": "28.3.9. Summary of evidence and recommendations for foetal urology",
      "anchor": "#28-3-9-summary-of-evidence-and-recommendations-for-foetal-urology"
    },
    {
      "level": 2,
      "text": "29. REFERENCES",
      "anchor": "#29-references"
    },
    {
      "level": 2,
      "text": "30. CONFLICT OF INTEREST",
      "anchor": "#30-conflict-of-interest"
    },
    {
      "level": 2,
      "text": "31. CITATION INFORMATION",
      "anchor": "#31-citation-information"
    },
    {
      "level": 2,
      "text": "32. COPYRIGHT AND TERMS OF USE",
      "anchor": "#32-copyright-and-terms-of-use"
    }
  ],
  "sections": [
    {
      "anchor": "#paediatric-urology",
      "title": "Paediatric Urology",
      "level": 1,
      "text": "Want to read the guideline in your own time? Download the PDF Download full guideline Looking for a quick overview? Check the pocket guidelines. Download pocket guidelines Searching... 22. Rare Conditions In Childhood Introduction Methods Phimosis And Other Abnormalities Of The Penile Skin Management Of Undescended Testes Testicular Tumours In Prepubertal Boys Fertility Preservation In Children And Adolescents Hydrocele Acute Scrotum Hypospadias Congenital Penile Curvature Varicocele In Children And Adolescents Urinary Tract Infections In Children Daytime Lower Urinary Tract Conditions Monosymptomatic Nocturnal Enuresis Bedwetting Spinal Dysraphism In Children And Adolescents Formally Neurogenic Bladder Dilatation Of The Upper Urinary Tract Puj Obstruction Vesicoureteric Reflux Urinary Stone Disease Ureterocele And Ectopic Ureter Disorders/differences Of Sex Development Congenital Lower Urinary Tract Obstruction Rare Conditions In Childhood Emergencies In Paediatric Urology Paediatric Urological Trauma Perioperative Management Basic Principles Of Laparoscopic Surgery In Children Transitional Urology Foetal Urology References Conflict Of Interest Citation Information Copyright And Terms Of Use",
      "tables": []
    },
    {
      "anchor": "#22-rare-conditions-in-childhood",
      "title": "22. RARE CONDITIONS IN CHILDHOOD",
      "level": 2,
      "text": "",
      "tables": []
    },
    {
      "anchor": "#22-1-urachal-remnants",
      "title": "22.1. Urachal remnants",
      "level": 3,
      "text": "",
      "tables": []
    },
    {
      "anchor": "#22-1-1-introduction",
      "title": "22.1.1. Introduction",
      "level": 4,
      "text": "The urachus is an embryonic structure arising as a result of the separation of the allantois from the ventral cloaca. The allantois appears on day 16 as a tiny, fingerlike outpouching from the caudal wall of the yolk sac, which is contiguous with the ventral cloaca at one end and the umbilicus at the other. The ventral portion of the cloaca develops into the bladder after cloacal division by the urogenital septum. Therefore, the bladder initially extends all the way to the umbilicus [1323]. With progressive foetal development, as the bladder descends towards the pelvis, the attachment between the umbilicus and the urachus becomes looser and the apical portion progressively narrows to a small, epithelialised, fibromuscular strand by the fourth or fifth month of gestation. The urachus then obliterates completely by birth, forming the median umbilical ligament [1324-1326]. The urachus varies from 3 to 10cm in length and from 8 to 10mm in diameter. It is a three-layered tubular structure, the innermost layer being lined with transitional epithelium, the middle layer composed of connective tissue, and the outermost muscular layer in continuity with the detrusor muscle [1327]. Urachal remnants (URs) originate from the failure of allantois obliteration, resulting in a urachal anomaly such as (1) urachal sinus, (2) urachal cyst, (3) vesicourachal diverticulum, or patent urachus [1324,1325,1328].",
      "tables": []
    },
    {
      "anchor": "#22-1-2-epidemiology",
      "title": "22.1.2. Epidemiology",
      "level": 4,
      "text": "The reported prevalence of URs is highly variable, possibly due to the use of different definitions of URs. For example, in a study with patients undergoing laparoscopy for inguinal hernia repair, all visible residual tissue was scored as a UR, and therefore a UR was visualised in 35.4% of patients, particularly in patients < 1 year (63.2%). All of these patients were asymptomatic [1329]. This supports a physiological regression of URs with age. In contrast, in a large study evaluating ultrasonographic exams in patients < 18 years old with specific attention focussed on diagnosing URs, the prevalence of URs was only 0.2% [1330]. The incidence rate in boys is slightly higher than in girls [1331,1332]. The subtypes of various URs reported in the literature is 10-48% for a patent urachus, 31-43% for a urachal cyst, 18-43% for a urachal sinus and 3-4% for a urachal diverticulum [1333,1334].",
      "tables": []
    },
    {
      "anchor": "#22-1-3-symptoms",
      "title": "22.1.3. Symptoms",
      "level": 4,
      "text": "Most often, the UR is asymptomatic. The most common symptom of a urachal remnant is umbilical granulation, discharge and erythema in infants and abdominal pain in older children [1333]. A patent urachus can cause continuous or intermittent urine leakage from the umbilicus, causing umbilical granulation and erythema [1333]. A urachal cyst is usually diagnosed (1) incidentally, or (2) when it becomes infected causing abdominal pain and discharge of pus from the umbilicus or recurrent UTIs when it drains into the bladder. Other symptoms of infected urachal anomalies can vary from high fever and abdominal pain to urinary tract infections, LUTS and/or an abdominal mass [1334-1338]. A urachal diverticulum is often asymptomatic and is usually found incidentally during investigations for other problems. Urachal remnants can have associated or simultaneous anomalies. In one study, these anomalies were found in 17 of 46 children, of which VUR was the most common (six patients) [1339].",
      "tables": []
    },
    {
      "anchor": "#22-1-4-diagnosis",
      "title": "22.1.4. Diagnosis",
      "level": 4,
      "text": "When a UR is suspected, a careful history and physical examination should be performed. In many patients, the diagnosis can be confirmed by US [1340]. However, in a retrospective study investigating 56 patients, the diagnostic accuracy of ultrasound to diagnose a UR or omphalomesenteric remnant in patients with umbilical discharge was shown to be relatively low (sensitivity 71.1%, specificity 72.2%, positive predicting value [PPV] 76.2%, negative predicting value [NPV] 66.7%) [1341]. A MRI or CT scan may be necessary in a minority of children for more detailed imaging [1337]. In general, a VCUG is only indicated when the child also presents with UTI or when the US shows signs of upper tract abnormalities [1342].",
      "tables": []
    },
    {
      "anchor": "#22-1-5-treatment",
      "title": "22.1.5. Treatment",
      "level": 4,
      "text": "If a UR is symptomatic, the standard approach is the surgical removal of the remnant. However, in children less than six months old, even when they are symptomatic, a conservative approach with observation and/or antibiotics is possible, since there is a high chance of spontaneous resolution [1333,1335,1338,1343,1344]. In the event of active inflammation/infection, this should be treated first, and surgery should preferably be performed as an elective procedure. A Pfannenstiel, periumbilical or infraumbilical midline incision can be used for the open surgical approach [1336,1345]. Alternatively, a laparoscopic or robotic approach has been shown to be safe and effective [1344,1346-1348]. Complication rates can vary with age. In one study, it was shown that operative management of younger patients resulted in more reoperations, readmissions and longer length of stay [1349], while in another study, patients had fewer complications when surgery was performed at < 1 year of age [1350]. Given that a conservative approach can be effective, it should precede an eventual surgical resection.",
      "tables": []
    },
    {
      "anchor": "#22-1-6-pathology-of-removed-remnants",
      "title": "22.1.6. Pathology of removed remnants",
      "level": 4,
      "text": "Removed specimens may show inflammation or a cystic structure [1335]. Patients presenting without symptoms are as likely to have epithelial elements in the UR as those presenting with symptoms [1337].",
      "tables": []
    },
    {
      "anchor": "#22-1-7-urachal-cancer",
      "title": "22.1.7. Urachal cancer",
      "level": 4,
      "text": "Urachal cancer has not been shown to occur in children. Urachal anomalies are thought to be associated with an increased risk of bladder adenocarcinoma in adults, and urachal adenocarcinoma has an estimated incidence of 0.18 per 100,000 individuals yearly [1351]. In a large database study, the most frequent tumour type was adenocarcinoma (65-82%) followed by urothelial carcinoma (UC) (11-21%) [1352]. Five-year survival was 54.8-64.4%. Urachal adenocarcinoma is very rare, especially when one considers that up to 62% of children under sixteen years of age may have a UR [1340,1353]. A study by Copp et al. found no association between the presence of UR symptoms and the presence or absence of epithelial tissue in pathology specimens, leading them to conclude that UR symptoms have poor predictive value for malignancy potential in these remnants [1332,1352]. Gleason et al. found that 5,721 URs would need to be excised to prevent a single case of urachal adenocarcinoma out of the nearly 65,000 patients reviewed [1351]. Assuming that epithelium is required in the development of urachal adenocarcinoma, the extrapolated number needed to treat (NNT) would be more than 8,000, as nearly 30% of urachal anomalies are void of an epithelial component. Fewer than 5% of urachal cancers have a nonepithelial origin such as sarcoma [1354]. At present, no long-term follow-up on untreated UR in children is available, and there is no evidence that urachal anomalies in children increase the likelihood of future malignancy [1333,1355].",
      "tables": []
    },
    {
      "anchor": "#22-1-8-summary-of-evidence-and-recommendation-for-management-of-urachal-remnants",
      "title": "22.1.8. Summary of evidence and recommendation for management of urachal remnants",
      "level": 4,
      "text": "Summary of evidence LE Most often, the urachal remnant is asymptomatic, but when symptomatic, the most common symptom of a urachal remnant is umbilical granulation, discharge and erythema in infants and abdominal pain in older children. 3 When a urachal remnant is suspected, a careful history and physical examination should be performed, and in many patients, the diagnosis can be supported by ultrasound. 3 Urachal remnants carry no known risk of malignant transformation during childhood and a very low overall lifetime risk. 3 Recommendations Strength rating Manage asymptomatic urachal remnants (UR) conservatively. Strong Manage symptomatic URs initially conservatively with observation and/or antibiotics, and preferably with elective surgical removal if persistent. Weak Remove symptomatic URs using either an open, laparoscopic or robotic approach. Strong Do not perform a voiding cystourethrography in an asymptomatic UR. Weak",
      "tables": [
        {
          "rows": [
            [
              "Summary of evidence",
              "LE"
            ],
            [
              "Most often, the urachal remnant is asymptomatic, but when symptomatic, the most common symptom of a urachal remnant is umbilical granulation, discharge and erythema in infants and abdominal pain in older children.",
              "3"
            ],
            [
              "When a urachal remnant is suspected, a careful history and physical examination should be performed, and in many patients, the diagnosis can be supported by ultrasound.",
              "3"
            ],
            [
              "Urachal remnants carry no known risk of malignant transformation during childhood and a very low overall lifetime risk.",
              "3"
            ]
          ]
        },
        {
          "rows": [
            [
              "Recommendations",
              "Strength rating"
            ],
            [
              "Manage asymptomatic urachal remnants (UR) conservatively.",
              "Strong"
            ],
            [
              "Manage symptomatic URs initially conservatively with observation and/or antibiotics, and preferably with elective surgical removal if persistent.",
              "Weak"
            ],
            [
              "Remove symptomatic URs using either an open, laparoscopic or robotic approach.",
              "Strong"
            ],
            [
              "Do not perform a voiding cystourethrography in an asymptomatic UR.",
              "Weak"
            ]
          ]
        }
      ]
    },
    {
      "anchor": "#22-2-papillary-tumours-of-the-bladder-in-children-and-adolescents-papillary-urothelial-neoplasm-of-low-malignant-potential",
      "title": "22.2. Papillary tumours of the bladder in children and adolescents (Papillary urothelial neoplasm of low malignant potential)",
      "level": 3,
      "text": "",
      "tables": []
    },
    {
      "anchor": "#22-2-1-incidence",
      "title": "22.2.1. Incidence",
      "level": 4,
      "text": "Papillary tumours of the bladder in children and adolescents are extremely rare and differ from papillary tumours in adults. A ‘grape-like’ papillary tumour in young children is more likely to represent rhabdomyosarcoma of the bladder, which is not the focus of this guideline. Papillary tumours in older children or adolescents will more likely be papillary urothelial neoplasms of low malignant potential (PUNLMP) [1356]. Children with risk factors such as previous bladder surgery and immunosuppressive medication can also develop a nephrogenic adenoma of the bladder, also presenting as a papillary tumour of the bladder.",
      "tables": []
    },
    {
      "anchor": "#22-2-2-differences-and-similarities-of-papillary-tumours-of-the-bladder-in-children-and-adults",
      "title": "22.2.2. Differences and similarities of papillary tumours of the bladder in children and adults",
      "level": 4,
      "text": "Sex The overall the risk of a papillary tumour in the bladder in paediatric and young adult patients is approximately double in males compared to females [1357].",
      "tables": []
    },
    {
      "anchor": "#22-2-3-risk-factors",
      "title": "22.2.3. Risk factors",
      "level": 4,
      "text": "The majority of these patients have no identifiable risk factors [1358].",
      "tables": []
    },
    {
      "anchor": "#22-2-4-presentation",
      "title": "22.2.4. Presentation",
      "level": 4,
      "text": "The most common symptom at presentation is monosymptomatic haematuria. Other less-common symptoms include abdominal pain, storage LUTS including frequency, dysuria and at times obstructive symptoms [1357].",
      "tables": []
    },
    {
      "anchor": "#22-2-5-investigations-and-treatment",
      "title": "22.2.5. Investigations and treatment",
      "level": 4,
      "text": "Ultrasound of the genitourinary tract is the first investigation of choice. It is an excellent screening tool and can often accurately diagnose the nature and location of the lesion. In children and adolescents, a bladder US of the full bladder is more sensitive compared with adults due to reduced abdominal fat and thinner muscle layer [1359]. In the event of a need to differentiate the renal or bladder origin of the haematuria, a red blood cell morphology will reveal isomorphic blood cells, indicating a bladder origin. Urine cytology can be performed, however, it has very limited value, likely due to the low-grade nature of these tumours in children. If a bladder tumour is suspected on imaging, cystoscopy should be performed for simultaneous diagnosis and treatment, as well as transurethral resection of the tumour. In children, cystoscopy requires general anaesthesia [1360].",
      "tables": []
    },
    {
      "anchor": "#22-2-6-histology",
      "title": "22.2.6. Histology",
      "level": 4,
      "text": "All the lesions in the paediatric and adolescent age group are identified as papillary and over 85% are solitary [1359]. Papillary bladder tumours in patients younger than twenty years of age have low-grade non-invasive disease (WHO classification) [1361]. These findings allow pathologists to conclude that, in children and adolescents, a papillary bladder tumour can be classified as papillary urothelial neoplasm of low malignant potential (PUNLMP). Papillary urothelial neoplasm of low malignant potential has minimal or no cytological atypia and differs from low grade urothelial carcinoma (UC), which has cytologic atypia, hyperchromatic nuclei and scattered mitosis and is rare in children but should always be considered [1362,1363]. For optimal diagnosis and staging it is important that resection includes the detrusor. For resection technique and staging, see Chapter 22.1.",
      "tables": []
    },
    {
      "anchor": "#22-2-7-additional-treatment",
      "title": "22.2.7. Additional treatment",
      "level": 4,
      "text": "Despite lacking evidence, adjuvant instillations have been used sporadically in cases of paediatric UC [1357,1358,1364].",
      "tables": []
    },
    {
      "anchor": "#22-2-8-prognosis-recurrence-and-surveillance",
      "title": "22.2.8. Prognosis, recurrence and surveillance",
      "level": 4,
      "text": "Overall, the prognosis of papillary tumours of the bladder in children is good. The recurrence rate in children and adolescents varies from 8 to 15% [1356,1357,1359]. Mean time to recurrence can vary from 11 to 29 months depending on the study, with recurrences occurring up to 90 months from diagnosis, though 64% occur in the first year [1357]. In certain cases, recurrences can be aggressive [1359]. Follow-up strategies are based on the guidelines and protocols of papillary tumours of the bladder in adults. It is advised to follow-up children and adolescents with a history of a PUNLMP initially with a short interval of three to six months in the first year, and thereafter at least yearly, with urinalysis for haematuria and a US of the full bladder. In the event of sudden gross haematuria, the evaluation must be performed immediately. If the tumour was completely resected at primary surgery, standard follow-up cystoscopy is not necessary but should be performed in children or adolescents with any form of UC or suspected recurrence on bladder US [1359]. The exact duration of follow-up is unknown, but this Panel recommends follow-up for at least five years. Urine cytology has no place in follow-up. All cases should be managed in an MDT setting. Inflammatory myofibroblastic tumours of the bladder (IMTB) This type of tumour is rare, with nearly 200 cases reported in the literature [1365,1366]. Approximately 25% occur in children with a median age at diagnosis of 7.5 years and a median tumour size of 5.5cm. Boys and girls are equally affected [1367]. These tumours are usually benign, with only very few reported malignant cases [1368]. Treatment is mostly surgical with transurethral resection, but local resection or partial cystectomy may be required in selected cases [1367,1369]. Additionally, a conservative approach is reported [1370]. Histological examination is required to exclude other malignant tumours such as a rhabdomyosarcoma. In children, no recurrence has been reported so far. However, due to the malignant potential and few recurrences in adults, the same follow-up as for papillary bladder tumours is recommended. Eosinophilic cystitis Although well described in adults, the inflammatory condition eosinophilic cystitis is rare in the paediatric population, with fewer than 100 cases reported in the literature to date [1371]. Its aetiology remains unknown but is thought to be incited by immunoglobulin E-mediated attraction of eosinophils to the bladder wall, followed by mast cell degranulation. Eosinophilic cystitis has been linked to medications, specifically antibiotics such as penicillin, chemotherapeutic agents such as cyclophosphamide and mitomycin, and chronic bladder catheterisation [1372,1373]. In children, as opposed to adults, males are more frequently afflicted, with seven years being the mean age of presentation. However, the condition can be seen throughout childhood even in LUTS [1371,1374]. LUTS such as dysuria, frequency, urgency and incontinence are the most frequent and can mimic UTI [1375]. Other symptoms include haematuria, suprapubic tenderness and systemic symptoms. Obstructive manifestations due to mass formation in the bladder wall can result in ureteral obstruction leading to hydroureteronephrosis and suprapubic mass in infants in addition to voiding dysfunction [1371,1374,1376]. Although associated with allergy, only about a third of reported cases had a history of other allergic conditions, whereas half had significant eosinophilia or eosinophiluria. Diagnosis is often delayed as symptoms of eosinophilic cystitis (EC) mimic other more common conditions such as UTI and LUTS, and most patients will ultimately have undergone imaging studies such as ultrasound, VCUG, CT and MRI, which while not specially diagnostic for the condition, may show bladder wall thickening or even mass formation, with rhabdomyosarcoma constituting an important differential diagnosis. A high index of suspicion for the diagnosis should therefore be maintained when dealing with protracted urinary symptoms not responsive to conventional intervention. Definitive diagnosis can only be attained on tissue biopsy obtained by cystoscopy. Histologically, eosinophilic infiltration of lamina propria and muscularis are seen in acute phases with > 25 eosinophils per high power field considered to be significant [1371,1374,1376]. Management is not standardised. Removal of any possible allergens is the obvious first step and there are reports of self-limiting course of the disease. However, empirical treatment with corticosteroids, antibiotics, anticholinergics and antihistamines, in addition to cyclosporine A have been utilised and lead to resolution of symptoms in most cases. Partial cystectomy has been performed in circumscribed lesions that do not disappear spontaneously. No standard follow-up recommendations exist, however, surveillance is justified as recurrence has been reported in approximately a third of patients [1",
      "tables": []
    },
    {
      "anchor": "#22-2-9-summary-of-evidence-and-recommendations-for-papillary-tumours-of-the-bladder-in-children",
      "title": "22.2.9. Summary of evidence and recommendations for papillary tumours of the bladder in children",
      "level": 4,
      "text": "Summary of evidence LE The majority of paediatric patients have no identifiable risk factors for bladder tumours. 3 There is no evidence on intravesical therapy for bladder tumours in children and adolescents. 4 Overall, prognosis of papillary tumours of the bladder in children is good. 3 Inflammatory myofibroblastic bladder tumours are usually benign. 3 A third of paediatric eosinophilic cystitis (EC) cases are associated with a history of allergic conditions and 50% are associated with significant eosinophilia or eosinophiluria. 4 Paediatric EC patients usually present with irritative and or obstructive urinary symptoms, which can mimic UTI or LUTS, thereby leading to delayed diagnosis. 4 In paediatric EC, definitive diagnosis can only be attained on tissue biopsy obtained by means of cystoscopy. 4 In EC, treatment with corticosteroids, antibiotics, anticholinergics and antihistamines, in addition to cyclosporine A, have been utilised and lead to resolution of symptoms in most cases. 4 No standard follow-up recommendations exist, however, surveillance is justified as recurrence has been reported in approximately a third of patients. 4 Nephrogenic adenoma in children are rare benign lesions that usually occur in the setting of previous surgery or chronic irritation of urinary tract and mainly occurring in the bladder. 4 Nephrogenic adenoma usually presents with haematuria and or storage LUTS and with a papillary/polypoid mass seen on cystoscopy. 4 Nephrogenic adenoma diagnosis is established by cystoscopy and histopathological review of biopsy specimen. 4 Nephrogenic adenoma treatment is excision either by transurethral resection (which often requires reresections), partial cystectomy or open excision. 4 Nephrogenic adenoma A recurrence rate is high, therefore justifying regular follow-up. 4 Recommendations Strength rating Ultrasound is the first investigation of choice for the diagnosis of paediatric bladder tumours. Strong Cystoscopy should be reserved if a bladder tumour is suspected on imaging for diagnosis and treatment. Strong After histological confirmation, inflammatory myofibroblastic bladder tumours should be resected locally. Weak Follow-up should be every three to six months in the first year, and at least annually thereafter, with urinalysis and an ultrasound for at least five years. Weak Have a high index of suspicion of eosinophilic cystitis (EC) in protracted urinary tract symptoms unresponsive to regular treatment. Strong Remove any possible allergens as the obvious first step in managing EC. Strong Eosinophilic cystitis can be managed medically with corticosteroids, antibiotics, anticholinergics and antihistamines, in addition to cyclosporine A. Weak Manage nephrogenic adenoma (NA) by resection either transuretherally or by open excision. Strong Regular endoscopic follow-up especially for augmented patients with NA is justified. Weak",
      "tables": [
        {
          "rows": [
            [
              "Summary of evidence",
              "LE"
            ],
            [
              "The majority of paediatric patients have no identifiable risk factors for bladder tumours.",
              "3"
            ],
            [
              "There is no evidence on intravesical therapy for bladder tumours in children and adolescents.",
              "4"
            ],
            [
              "Overall, prognosis of papillary tumours of the bladder in children is good.",
              "3"
            ],
            [
              "Inflammatory myofibroblastic bladder tumours are usually benign.",
              "3"
            ],
            [
              "A third of paediatric eosinophilic cystitis (EC) cases are associated with a history of allergic conditions and 50% are associated with significant eosinophilia or eosinophiluria.",
              "4"
            ],
            [
              "Paediatric EC patients usually present with irritative and or obstructive urinary symptoms, which can mimic UTI or LUTS, thereby leading to delayed diagnosis.",
              "4"
            ],
            [
              "In paediatric EC, definitive diagnosis can only be attained on tissue biopsy obtained by means of cystoscopy.",
              "4"
            ],
            [
              "In EC, treatment with corticosteroids, antibiotics, anticholinergics and antihistamines, in addition to cyclosporine A, have been utilised and lead to resolution of symptoms in most cases.",
              "4"
            ],
            [
              "No standard follow-up recommendations exist, however, surveillance is justified as recurrence has been reported in approximately a third of patients.",
              "4"
            ],
            [
              "Nephrogenic adenoma in children are rare benign lesions that usually occur in the setting of previous surgery or chronic irritation of urinary tract and mainly occurring in the bladder.",
              "4"
            ],
            [
              "Nephrogenic adenoma usually presents with haematuria and or storage LUTS and with a papillary/polypoid mass seen on cystoscopy.",
              "4"
            ],
            [
              "Nephrogenic adenoma diagnosis is established by cystoscopy and histopathological review of biopsy specimen.",
              "4"
            ],
            [
              "Nephrogenic adenoma treatment is excision either by transurethral resection (which often requires reresections), partial cystectomy or open excision.",
              "4"
            ],
            [
              "Nephrogenic adenoma A recurrence rate is high, therefore justifying regular follow-up.",
              "4"
            ]
          ]
        },
        {
          "rows": [
            [
              "Recommendations",
              "Strength rating"
            ],
            [
              "Ultrasound is the first investigation of choice for the diagnosis of paediatric bladder tumours.",
              "Strong"
            ],
            [
              "Cystoscopy should be reserved if a bladder tumour is suspected on imaging for diagnosis and treatment.",
              "Strong"
            ],
            [
              "After histological confirmation, inflammatory myofibroblastic bladder tumours should be resected locally.",
              "Weak"
            ],
            [
              "Follow-up should be every three to six months in the first year, and at least annually thereafter, with urinalysis and an ultrasound for at least five years.",
              "Weak"
            ],
            [
              "Have a high index of suspicion of eosinophilic cystitis (EC) in protracted urinary tract symptoms unresponsive to regular treatment.",
              "Strong"
            ],
            [
              "Remove any possible allergens as the obvious first step in managing EC.",
              "Strong"
            ],
            [
              "Eosinophilic cystitis can be managed medically with corticosteroids, antibiotics, anticholinergics and antihistamines, in addition to cyclosporine A.",
              "Weak"
            ],
            [
              "Manage nephrogenic adenoma (NA) by resection either transuretherally or by open excision.",
              "Strong"
            ],
            [
              "Regular endoscopic follow-up especially for augmented patients with NA is justified.",
              "Weak"
            ]
          ]
        }
      ]
    },
    {
      "anchor": "#22-3-penile-rare-conditions",
      "title": "22.3. Penile rare conditions",
      "level": 3,
      "text": "Paediatric lesions of the penis are uncommon, but an important part of the paediatric urological practice. The most common of these lesions are cystic penile lesions followed by vascular malformations and neurogenic lesions [1380]. Soft tissue tumours of the male external genitalia are uncommon but have been described in the paediatric age group and can be malignant [1381].",
      "tables": []
    },
    {
      "anchor": "#22-3-1-cystic-lesions",
      "title": "22.3.1. Cystic lesions",
      "level": 4,
      "text": "Epidermal inclusion cysts Epidermal inclusion cysts are the most common genital cystic lesion and can occur anywhere on the body in both men and women. In the penis, these types of cysts occur most commonly over the penile shaft, varying from 0.1 to 1cm in diameter. The epithelium of these cysts is lined and filled with keratin. It is a painless swelling and can present in the age group with a history of circumcision. Treatment by total surgical excision is mainly indicated for cosmetic or symptomatic (e.g. infection) reasons and should be performed without rupturing the cyst to avoid recurrence [1382]. Mucoid cyst of the penis Mucoid cysts are synonymous with parameatal cyst or genitoperineal cyst of median raphe. Mucoid cysts are midline developmental cysts arising from ectopic urethral mucosa filled with mucoid material. These types of cysts present starting at birth but are usually detected during adolescence or later. These cysts are usually asymptomatic, developing over the penile ventral surface around the glans and require surgical removal for either cosmetic, functional or symptomatic reasons [1383]. Median raphe cysts These types of cysts arise from incomplete closure of the genital fold during embryogenesis; they are commonly diagnosed in the first decade of life but can present later as they tend to be asymptomatic [1384]. They are either unilocular or multilocular fluid containing cysts, with a mean size of 0.8cm, but cysts larger than 2cm have also been reported [1385]. Cysts are centred in dermis, with no connection to urethra or epidermis. Histopathologically, there are four types: urethral (urothelium-like epithelium, account for 55% cases), as well as epidermoid, glandular and mixed. Epidermoid cysts may be congenital or acquired. Acquired penile epidermoid cysts (PECs) occur by traumatic implantation of the epidermal components into the dermis, usually as a result of surgical procedures such as circumcision and hypospadias repair [1386]. Median raphe cysts can be treated conservatively and can resolve spontaneously or persist. Cyst aspiration is associated with high risk of recurrence and surgical excision is the treatment of choice. Although most penile cysts are asymptomatic, these types of cysts may become infected, resulting in pain and tenderness. They can also present with ulceration, rupture and urinary obstruction if they are close to the urethral meatus. This, along with cosmetic issues, leads most caregivers and patients to opt for surgical excision. Smegmal cysts or smegmal pearls Smegmal cysts can be a differential for aforementioned cysts. Smegmal cysts are a benign collection of smegma in the subpreputial space in uncircumcised boys with anticipated spontaneous resolution [1387]. Dermoid cysts Dermoid cysts are congenital, asymptomatic, firm, solitary, subcutaneous cystic lesions occurring commonly in the region of the corona involving the foreskin. Histopathologically, these types of cysts contain sweat and sebaceous glands, with elements of hair and squamous epithelium. Pilosebaceous cysts have been described on the glans. These cysts are benign and usually diagnosed after excision.",
      "tables": []
    },
    {
      "anchor": "#22-3-2-vascular-malformations",
      "title": "22.3.2. Vascular malformations",
      "level": 4,
      "text": "A broad classification of penile vascular lesions into haemangiomas and vascular malformations was proposed by Ramos in 1999 [1388]. Haemangiomas develop rapidly at birth and involute slowly. Venous malformations are usually present at birth and slowly progress [1389]. Haemangiomas also include pyogenic granulomas, which are benign outgrowths of cutaneous capillary vessels formed usually from chronic irritation [1380]. The growth cycle of infantile haemangiomas is divided into early and late proliferative stages, followed by a slow involution phase, completing growth by the age of nine months [1390]. Propranolol (oral or topical) is currently first-line treatment for infantile haemangiomas. The exact mechanism of action is unknown but can include inhibition of angiogenesis and vasoconstriction, among others. The dose is in the range of 1.5-2.5mg/kg, which must be continued for 12 to 18 months and then tapered through active or passive weaning to reduce risk of rebound growth [1390]. Other factors leading to rebound growth after propranolol treatment include deep haemangiomas, which occur in approximately 38% of patients despite propranolol therapy, requiring local therapy such as topical timolol, pulsed dye laser or intralesional steroids. After twelve months, the median improvement with treatment is reported as 81% (range 70-90%), based on VAS scores of serial patient photographs. Vascular malformations are congenital lesions of capillary, lymphatic and venous (or slow-flow) or arterial/arteriovenous (fast-flow) origin that enlarge slowly as the patient grows. These malformations include glomus tumours, which are primarily congenital arteriovenous shunts that develop from thermoregulatory glomus bodies (fast-flow vascular malformations). Glomus tumours of the penis can arise on the glans penis, corpora of the penis and as periurethral masses, sometimes accompanied by glomus tumours of fingers and feet [1391]. These are usually asymptomatic at presentation or may have symptoms such as priapism, palpitation and perineal pain. Glomus tumours are benign despite exhibiting high-grade nuclear polymorphism. Vascular malformations are usually benign and managed conservatively. Treatment options include LASER, sclerotherapy [1389] or surgical excision [1392]. In the treatment of children’s penile venous malformations, relatively conservative and mild sclerosing agents, such as polidocanol, pingyangmycin or bleomycin, are recommended [1389]. However, glomus tumours specifically need surgical treatment and follow-up due to the risk of recurrence from incomplete excision [1393].",
      "tables": []
    },
    {
      "anchor": "#22-3-3-neurogenic-lesions",
      "title": "22.3.3. Neurogenic lesions",
      "level": 4,
      "text": "Penile neurofibroma (PNF) is an extremely rare lesion arising from perineural and Schwann cells and usually occurs with evidence of systemic neurofibromatosis or Von Recklinghausen syndrome [1394]. Neurogenic lesions are successfully treated with complete excision [1380]. It should be noted that penile schwannomas in children may differ from those in adults, as they may grow faster and be bound up with genetic syndromes or certain specific tumours that affect intelligence [1395]. Rare cases of malignant schwannomas on the penis, presumably secondary to malignant transformation of benign neurofibromas, have been reported in boys with a strong family history of neurofibromatosis. This type of malignant degeneration of neurofibromatosis reportedly occurs in 5-16% of children [1394]. Therefore, these patients require long-term follow-up due to risk of recurrence, new tumour formation and malignant transformation.",
      "tables": []
    },
    {
      "anchor": "#22-3-4-soft-tissue-tumours-of-penis",
      "title": "22.3.4. Soft tissue tumours of penis",
      "level": 4,
      "text": "Mesenchymal tumours are rare in the external genitalia, and they require excision to differentiate between benign and malignant neoplasms. Histopathological characterisation is essential to ensure that malignant tumours receive radical treatment with adjuvant therapy or close follow-up [1381]. Presentation is usually of a painless penile mass that is nontender and rubbery upon examination. Ultrasound may be useful in characterising the lesion but is not diagnostic. The ultrasound can exclude urethral invasion if it is close to the urethra [1381]. Once an excision biopsy is performed, if aggressive malignant components are found, a further wider resection may be required. Fibrosarcoma is a rare, non-rhabdomyosarcoma soft tissue tumour that arises from fibrous tissue. The infantile form of fibrosarcoma is rare and those occurring on the penis are even rarer in the paediatric age group. Surgical intervention has a favourable prognosis in the paediatric age group, with long-term survival of 90% in sporadic cases [1396]. Myofibroma is a benign congenital lesion that occurs either as a solitary lesion or as a part of myofibromatosis with multiple soft tissue tumours. Excision is necessary for histological diagnosis [1381]. Primary penile teratomas are an extremely rare subtype of congenital germ cell tumours, and they tend to be asymptomatic and are subdermal on US with no blood flow on Doppler [1397]. These teratomas require aggressive treatment with surgical resection due to their unpredictable behaviour and unresponsiveness to chemotherapy. Mature teratomas are benign, but immature teratoma, or even mixed teratomas with immature components, can turn malignant and have the potential to metastasise and recur.",
      "tables": []
    },
    {
      "anchor": "#22-3-5-penile-lymphedema",
      "title": "22.3.5. Penile lymphedema",
      "level": 4,
      "text": "Lymphedema in adults is usually secondary to malignancy or infectious disease affecting lymphatic drainage. In the paediatric age group, however, lymphedema is usually primary and generally very rare, affecting 1.2 per 100,000 persons under the age of 20 years [1398]. Of these, only a very small fraction relates to the genital region. Regardless of underlying aetiology, inefficient lymphatic drainage leads to accumulation of subcutaneous lymph, which causes tissue swelling and inflammation. This in turn stimulates adipose deposition and fibrosis, further exacerbating enlargement. With time, the oedematous tissue becomes vulnerable to infection, chronic cutaneous changes and disfigurement [1399]. Additionally, when occurring in the genital region, urological complications may ensue, such as phimosis, haematuria, bleeding, bladder outlet obstruction, pain, dysuria, lymphorrhea and severe psychological distress due to resultant deformity [1400,1401]. In the largest cohort of male genital oedema in the paediatric age group, 92% of cases were primary. Of these, only 25% had a discernible familial or syndromic association, such as Noonan syndrome, lymphedema-distichiasis or Milroy disease [1400]. Secondary genital lymphedema in children has been reported after inguinal surgery and noncaseating granulomatous lymphangitis as seen with metastatic Crohn’s disease [1400-1402]. Average age of onset was reported to be from 4.5 to ± 6.3 years, with 61% of cases presenting in infancy, 13% in childhood and the remaining 26% in adolescence. Oedema is usually penoscrotal in 72% of cases, isolated scrotal in 24% and very rarely confined exclusively to the penis in 4%. Moreover, concomitant lower limb oedema is the rule in two-thirds of cases [1400]. There is no general consensus on diagnostic workup of these patients. History and physical examination (including family history) is usually sufficient. However, lymphoscintigraphy can be used as a confirmatory test, more so for limb than genital oedema, where results can be difficult to interpret [1400]. Ultrasonography is nonspecific but has been advocated by some to exclude secondary lymphedema by examining the patency of iliac and caval vessels [1403]. Magnetic resonance imaging is useful to exclude other differential diagnoses, such as other venous or lymphatic anomalies [1400]. Conservative treatment is the accepted first-line treatment. The mainstay is compression therapy to maintain and prevent further swelling. This can be achieved by compression stockings and undergarments. Additionally, close observation and protection of the skin to prevent excoriations and infection is essential [1400,1403]. Compression therapy is, however, less effective on genital oedema than it is on limb oedema, particularly in growing children. When conservative management fails, and particularly in symptomatic cases, or in patients with functional impairment, surgical debulking may be necessary. This can either take the form of circumcision in cases in which the foreskin is affected or excision of affected skin and subcutaneous tissues with restructuring and contouring for optimal cosmetic outcome. Complete skin excision and grafting may also be required [1400-1403]. Surgical management can be challenging and must be restricted to patients with significant symptoms. Complications include recurrences, continuous lymphatic leakage, haematoma, infection and poor cosmetic outcome [1398,1403,1404]. Summary of evidence LE Cystic penile lesions are the most common paediatric penile lesions, followed by vascular malformations and neurogenic lesions. 3 Neurofibroma patients require long-term follow-up due to risk of recurrence, new tumour formation and malignant transformation. 3 Mesenchymal tumours are rare and require excision to differentiate between benign and malignant neoplasms. 3 Recommendations Strength rating Treatment of penile cystic lesions is by total surgical excision. It is mainly indicated for cosmetic or symptomatic reasons, e.g. infection. Weak Propranolol is currently first-line treatment for infantile haemangiomas. Strong Conservative management is the first-line treatment for penile lymphedema. Strong In symptomatic cases or in patients with functional impairment, surgical intervention may become necessary for penile lymphedema. Weak",
      "tables": [
        {
          "rows": [
            [
              "Summary of evidence",
              "LE"
            ],
            [
              "Cystic penile lesions are the most common paediatric penile lesions, followed by vascular malformations and neurogenic lesions.",
              "3"
            ],
            [
              "Neurofibroma patients require long-term follow-up due to risk of recurrence, new tumour formation and malignant transformation.",
              "3"
            ],
            [
              "Mesenchymal tumours are rare and require excision to differentiate between benign and malignant neoplasms.",
              "3"
            ]
          ]
        },
        {
          "rows": [
            [
              "Recommendations",
              "Strength rating"
            ],
            [
              "Treatment of penile cystic lesions is by total surgical excision. It is mainly indicated for cosmetic or symptomatic reasons, e.g. infection.",
              "Weak"
            ],
            [
              "Propranolol is currently first-line treatment for infantile haemangiomas.",
              "Strong"
            ],
            [
              "Conservative management is the first-line treatment for penile lymphedema.",
              "Strong"
            ],
            [
              "In symptomatic cases or in patients with functional impairment, surgical intervention may become necessary for penile lymphedema.",
              "Weak"
            ]
          ]
        }
      ]
    }
  ],
  "tables_count": 6
}